{
	"name": "Tile Map2-1",
	"cells": [
	    {
	        "x": 116,
	        "y": 4,
	        "w": 48,
	        "h": 48,
	        "name": "502823636"
	    },
	    {
	        "x": 60,
	        "y": 60,
	        "w": 48,
	        "h": 48,
	        "name": "502823638"
	    },
	    {
	        "x": 4,
	        "y": 60,
	        "w": 48,
	        "h": 48,
	        "name": "502823639"
	    },
	    {
	        "x": 60,
	        "y": 4,
	        "w": 48,
	        "h": 48,
	        "name": "502823640"
	    },
	    {
	        "x": 4,
	        "y": 4,
	        "w": 48,
	        "h": 48,
	        "name": "502823637"
	    }
    ]
}